refir/__init__.py
refir/constants.py
refir/refir.py
Refir-1.1.dist-info/METADATA
Refir-1.1.dist-info/WHEEL
Refir-1.1.dist-info/top_level.txt
Refir-1.1.dist-info/RECORD
