Metadata-Version: 2.1
Name: Refir
Version: 1.1
Summary: Add referral to your app with ease. With refir you can grow your user-base by aloowing your users to refer friends
Requires-Dist: requests
